ha_magiwand
